hoodpay_py/__init__.py
hoodpay_py/client.py
hoodpay_py/exceptions.py
hoodpay_py/resources/customers.py
hoodpay_py/resources/live_payments.py
hoodpay_py/resources/payments.py
hoodpay_py/types.py
hoodpay_py-0.1.0.dist-info/METADATA
hoodpay_py-0.1.0.dist-info/WHEEL
hoodpay_py-0.1.0.dist-info/licenses/LICENSE
hoodpay_py-0.1.0.dist-info/RECORD
