Metadata-Version: 2.4
Name: hoodpay-py
Version: 0.1.0
Summary: Lightweight Python SDK for the HoodPay API
License-File: LICENSE
Author: Alex
Author-email: a.marshall@tutamail.com
Requires-Python: >=3.8
Classifier: Programming Language :: Python :: 3
Classifier: Programming Language :: Python :: 3.8
Classifier: Programming Language :: Python :: 3.9
Classifier: Programming Language :: Python :: 3.10
Classifier: Programming Language :: Python :: 3.11
Classifier: Programming Language :: Python :: 3.12
Classifier: Programming Language :: Python :: 3.13
Classifier: Programming Language :: Python :: 3.14
Requires-Dist: requests (>=2.31.0,<3.0.0)
Requires-Dist: typing-extensions (>=4.5.0,<5.0.0) ; python_version < "3.10"
